{
    "level": 2, 
    "cost": 0, 
    "children": [
        {
            "level": 1, 
            "cost": 261, 
            "children": [
                {
                    "level": 0, 
                    "cost": 439, 
                    "children": [], 
                    "id": 1, 
                    "period": 700
                }, 
                {
                    "level": 0, 
                    "cost": 0, 
                    "children": [], 
                    "id": 0, 
                    "period": 7000
                }
            ], 
            "id": 6, 
            "period": 700
        }, 
        {
            "level": 1, 
            "cost": 89, 
            "children": [
                {
                    "level": 0, 
                    "cost": 161, 
                    "children": [], 
                    "id": 4, 
                    "period": 250
                }
            ], 
            "id": 5, 
            "period": 250
        }, 
        {
            "level": 1, 
            "cost": 949, 
            "children": [
                {
                    "level": 0, 
                    "cost": 167, 
                    "children": [], 
                    "id": 2, 
                    "period": 280
                }, 
                {
                    "level": 0, 
                    "cost": 927, 
                    "children": [], 
                    "id": 3, 
                    "period": 7000
                }
            ], 
            "id": 7, 
            "period": 3500
        }
    ], 
    "id": 8, 
    "period": 1
}