{
    "level": 1, 
    "cost": 0, 
    "children": [
        {
            "level": 0, 
            "cost": 323, 
            "children": [], 
            "id": 1, 
            "period": 500
        }, 
        {
            "level": 0, 
            "cost": 177, 
            "children": [], 
            "id": 2, 
            "period": 500
        }, 
        {
            "level": 0, 
            "cost": 0, 
            "children": [], 
            "id": 0, 
            "period": 200
        }, 
        {
            "level": 0, 
            "cost": 0, 
            "children": [], 
            "id": 3, 
            "period": 1750
        }
    ], 
    "id": 4, 
    "period": 1
}